Workbook

Sheet 00_Control
A1: Model Name: Shoprite Financial Forecast & Valuation
A3: Prepared by: Saun Sibanyoni
A4: Base Currency: ZAR (R million)
A5: Historical Period: FY2023-FY2025
A6: Forecast Period: FY2026-FY2030
A7: Valuation Date: FY2025 year-end
A8: Methodology: DCF + Multiples (Cross-check)
A9: Version: v1.0

Sheet 01_Historical_Input
A1: Item | B1: FY2023 | C1: FY2024 | D1: FY2025
A2: Revenue | B2: 219530 | C2: 246082 | D2: 256682
A3: Operating profit | B3: 12344 | C3: 13156 | D3: 14943
A4: Profit after tax | B4: 6320 | C4: 6543 | D4: 7392
A5: Operating cash flow | B5: 9831 | C5: 13841 | D5: 10984
A6: Capital expenditure | B6: 6229 | C6: 6779 | D6: 7365
A7: Total assets | B7: 102356 | C7: 112328 | D7: 124944
A8: Total equity | B8: 26278 | C8: 27724 | D8: 30117
A9: Total liabilities | B9: 76078 | C9: 84604 | D9: 94827
A10: Cash & cash equivalents | B10: 12548 | C10: 11732 | D10: 9946
A11: Interest-bearing borrowings | B11: 6368 | C11: 5993 | D11: 6993
A12: Shares outstanding (millions) | D12: 591.34

Sheet 02_Key_Assumptions_Bear
A1: Assumption | B1: Value | C1: Notes
A2: Revenue Growth FY2026 | B2: 0.08
A3: Revenue Growth FY2027 | B3: 0.07
A4: Revenue Growth FY2028 | B4: 0.06
A5: Revenue Growth FY2029 | B5: 0.05
A6: Revenue Growth FY2030 | B6: 0.05
A8: Operating Margin | B8: 0.058
A9: Tax Rate | B9: 0.27
A11: Operating Cash Flow Margin | B11: 0.05
A12: Capex % of Revenue | B12: 0.035
A14: WACC | B14: 0.13
A15: Terminal Growth Rate | B15: 0.025
A16: Forecast Period (Years) | B16: 5
A18: Shares outstanding (millions) | B18: 591.34

Sheet 02_Key_Assumptions_Base
A1: Assumption | B1: Value | C1: Notes
A2: Revenue Growth FY2026 | B2: 0.08
A3: Revenue Growth FY2027 | B3: 0.07
A4: Revenue Growth FY2028 | B4: 0.06
A5: Revenue Growth FY2029 | B5: 0.05
A6: Revenue Growth FY2030 | B6: 0.05
A8: Operating Margin | B8: 0.058
A9: Tax Rate | B9: 0.27
A11: Operating Cash Flow Margin | B11: 0.055
A12: Capex % of Revenue | B12: 0.03
A14: WACC | B14: 0.12
A15: Terminal Growth Rate | B15: 0.03
A16: Forecast Period (Years) | B16: 5
A18: Shares outstanding (millions) | B18: 591.34

Sheet 02_Key_Assumptions_Bull
A1: Assumption | B1: Value | C1: Notes
A2: Revenue Growth FY2026 | B2: 0.08
A3: Revenue Growth FY2027 | B3: 0.07
A4: Revenue Growth FY2028 | B4: 0.06
A5: Revenue Growth FY2029 | B5: 0.05
A6: Revenue Growth FY2030 | B6: 0.05
A8: Operating Margin | B8: 0.058
A9: Tax Rate | B9: 0.27
A11: Operating Cash Flow Margin | B11: 0.06
A12: Capex % of Revenue | B12: 0.028
A14: WACC | B14: 0.11
A15: Terminal Growth Rate | B15: 0.035
A16: Forecast Period (Years) | B16: 5
A18: Shares outstanding (millions) | B18: 591.34

Sheet 02_Key_Assumptions
A1: Assumption | B1: Value | C1: Notes
A2: Revenue Growth FY2026 | B2: 0.08
A3: Revenue Growth FY2027 | B3: 0.07
A4: Revenue Growth FY2028 | B4: 0.06
A5: Revenue Growth FY2029 | B5: 0.05
A6: Revenue Growth FY2030 | B6: 0.05
A8: Operating Margin | B8: 0.058
A9: Tax Rate | B9: 0.27
A11: Operating Cash Flow Margin | B11: 0.045
A12: Capex % of Revenue | B12: 0.04
A14: WACC | B14: 0.12
A15: Terminal Growth Rate | B15: 0.03
A16: Forecast Period (Years) | B16: 5
A18: Shares outstanding (millions) | B18: 591.34

Sheet 03_Revenue_Forecast
A1: Year | B1: Revenue | C1: Growth %
A2: FY2023 | B2: ='01_Historical_Input'!B2 -> 219530
A3: FY2024 | B3: ='01_Historical_Input'!C2 -> 246082 | C3: =(B3/B2)-1 -> 0.1209493
A4: FY2025 | B4: ='01_Historical_Input'!D2 -> 256682 | C4: =(B4/B3)-1 -> 0.043075073
A5: FY2026 | B5: =B4*(1+C5) -> 277216.56 | C5: ='02_Key_Assumptions'!B2 -> 0.08
A6: FY2027 | B6: =B5*(1+C6) -> 296621.72 | C6: ='02_Key_Assumptions'!B3 -> 0.07
A7: FY2028 | B7: =B6*(1+C7) -> 314419.02 | C7: ='02_Key_Assumptions'!B4 -> 0.06
A8: FY2029 | B8: =B7*(1+C8) -> 330139.97 | C8: ='02_Key_Assumptions'!B5 -> 0.05
A9: FY2030 | B9: =B8*(1+C9) -> 346646.97 | C9: ='02_Key_Assumptions'!B6 -> 0.05

Sheet 04_Costs_&_Margins
A1: Year | B1: FY2026 | C1: FY2027 | D1: FY2028 | E1: FY2029 | F1: FY2030
A2: Revenue | B2: ='03_Revenue_Forecast'!B5 -> 277216.56 | C2: ='03_Revenue_Forecast'!B6 -> 296621.72 | D2: ='03_Revenue_Forecast'!B7 -> 314419.02 | E2: ='03_Revenue_Forecast'!B8 -> 330139.97 | F2: ='03_Revenue_Forecast'!B9 -> 346646.97
A3: Operating margin | B3: ='02_Key_Assumptions'!$B$8 -> 0.058 | C3: ='02_Key_Assumptions'!$B$8 -> 0.058 | D3: ='02_Key_Assumptions'!$B$8 -> 0.058 | E3: ='02_Key_Assumptions'!$B$8 -> 0.058 | F3: ='02_Key_Assumptions'!$B$8 -> 0.058
A4: Operating profit | B4: =B2*B3 -> 16078.56 | C4: =C2*C3 -> 17204.06 | D4: =D2*D3 -> 18236.303 | E4: =E2*E3 -> 19148.118 | F4: =F2*F3 -> 20105.524
A5: Tax rate | B5: ='02_Key_Assumptions'!$B$9 -> 0.27 | C5: ='02_Key_Assumptions'!$B$9 -> 0.27 | D5: ='02_Key_Assumptions'!$B$9 -> 0.27 | E5: ='02_Key_Assumptions'!$B$9 -> 0.27 | F5: ='02_Key_Assumptions'!$B$9 -> 0.27
A6: Tax expense | B6: =B4*B5 -> 4341.2113 | C6: =C4*C5 -> 4645.0961 | D6: =D4*D5 -> 4923.8019 | E6: =E4*E5 -> 5169.992 | F6: =F4*F5 -> 5428.4916
A7: Profit after tax | B7: =B4-B6 -> 11737.349 | C7: =C4-C6 -> 12558.964 | D7: =D4-D6 -> 13312.501 | E7: =E4-E6 -> 13978.126 | F7: =F4-F6 -> 14677.033
A8: Net margin % | B8: =B7/B2 -> 0.04234 | C8: =C7/C2 -> 0.04234 | D8: =D7/D2 -> 0.04234 | E8: =E7/E2 -> 0.04234 | F8: =F7/F2 -> 0.04234

Sheet 05_Forecast_IS
A1: Line Item | B1: FY2026 | C1: FY2027 | D1: FY2028 | E1: FY2029 | F1: FY2030
A2: Revenue | B2: ='03_Revenue_Forecast'!B5 -> 277216.56 | C2: ='03_Revenue_Forecast'!B6 -> 296621.72 | D2: ='03_Revenue_Forecast'!B7 -> 314419.02 | E2: ='03_Revenue_Forecast'!B8 -> 330139.97 | F2: ='03_Revenue_Forecast'!B9 -> 346646.97
A3: Operating profit | B3: ='04_Costs_&_Margins'!B4 -> 16078.56 | C3: ='04_Costs_&_Margins'!C4 -> 17204.06 | D3: ='04_Costs_&_Margins'!D4 -> 18236.303 | E3: ='04_Costs_&_Margins'!E4 -> 19148.118 | F3: ='04_Costs_&_Margins'!F4 -> 20105.524
A4: Tax expense | B4: ='04_Costs_&_Margins'!B6 -> 4341.2113 | C4: ='04_Costs_&_Margins'!C6 -> 4645.0961 | D4: ='04_Costs_&_Margins'!D6 -> 4923.8019 | E4: ='04_Costs_&_Margins'!E6 -> 5169.992 | F4: ='04_Costs_&_Margins'!F6 -> 5428.4916
A5: Profit after tax | B5: ='04_Costs_&_Margins'!B7 -> 11737.349 | C5: ='04_Costs_&_Margins'!C7 -> 12558.964 | D5: ='04_Costs_&_Margins'!D7 -> 13312.501 | E5: ='04_Costs_&_Margins'!E7 -> 13978.126 | F5: ='04_Costs_&_Margins'!F7 -> 14677.033
A6: Net margin % | B6: =B5/B2 -> 0.04234 | C6: =C5/C2 -> 0.04234 | D6: =D5/D2 -> 0.04234 | E6: =E5/E2 -> 0.04234 | F6: =F5/F2 -> 0.04234

Sheet 06_Forecast_CF_Base
A1: Year | B1: FY2026 | C1: FY2027 | D1: FY2028 | E1: FY2029 | F1: FY2030
A2: Revenue | B2: ='03_Revenue_Forecast'!B5 -> 277216.56 | C2: ='03_Revenue_Forecast'!B6 -> 296621.72 | D2: ='03_Revenue_Forecast'!B7 -> 314419.02 | E2: ='03_Revenue_Forecast'!B8 -> 330139.97 | F2: ='03_Revenue_Forecast'!B9 -> 346646.97
A3: Operating cash flow | B3: 15246.911 | C3: 16314.195 | D3: 17293.046 | E3: 18157.699 | F3: 19065.583
A4: Capex | B4: 8316.4968 | C4: 8898.6516 | D4: 9432.5707 | E4: 9904.1992 | F4: 10399.409
A5: Free cash flow | B5: 6930.414 | C5: 7415.543 | D5: 7860.4756 | E5: 8253.4993 | F5: 8666.1743

Sheet 06_Forecast_CF_Bull
A1: Year | B1: FY2026 | C1: FY2027 | D1: FY2028 | E1: FY2029 | F1: FY2030
A2: Revenue | B2: ='03_Revenue_Forecast'!B5 -> 277216.56 | C2: ='03_Revenue_Forecast'!B6 -> 296621.72 | D2: ='03_Revenue_Forecast'!B7 -> 314419.02 | E2: ='03_Revenue_Forecast'!B8 -> 330139.97 | F2: ='03_Revenue_Forecast'!B9 -> 346646.97
A3: Operating cash flow | B3: 16632.994 | C3: 17797.303 | D3: 18865.141 | E3: 19808.398 | F3: 20798.818
A4: Capex | B4: 7762.0637 | C4: 8305.4081 | D4: 8803.7326 | E4: 9243.9193 | F4: 9706.1152
A5: Free cash flow | B5: 8870.9299 | C5: 9491.895 | D5: 10061.409 | E5: 10564.479 | F5: 11092.703

Sheet 06_Forecast_CF_Bear
A1: Year | B1: FY2026 | C1: FY2027 | D1: FY2028 | E1: FY2029 | F1: FY2030
A2: Revenue | B2: ='03_Revenue_Forecast'!B5 -> 277216.56 | C2: ='03_Revenue_Forecast'!B6 -> 296621.72 | D2: ='03_Revenue_Forecast'!B7 -> 314419.02 | E2: ='03_Revenue_Forecast'!B8 -> 330139.97 | F2: ='03_Revenue_Forecast'!B9 -> 346646.97
A3: Operating cash flow | B3: 13860.828 | C3: 14831.086 | D3: 15720.951 | E3: 16506.999 | F3: 17332.349
A4: Capex | B4: 9702.5796 | C4: 10381.76 | D4: 11004.666 | E4: 11554.899 | F4: 12132.644
A5: Free cash flow | B5: 4158.2484 | C5: 4449.3258 | D5: 4716.2853 | E5: 4952.0996 | F5: 5199.7046

Sheet 06_Forecast_CF
A1: Year | B1: FY2026 | C1: FY2027 | D1: FY2028 | E1: FY2029 | F1: FY2030
A2: Revenue | B2: ='03_Revenue_Forecast'!B5 -> 277216.56 | C2: ='03_Revenue_Forecast'!B6 -> 296621.72 | D2: ='03_Revenue_Forecast'!B7 -> 314419.02 | E2: ='03_Revenue_Forecast'!B8 -> 330139.97 | F2: ='03_Revenue_Forecast'!B9 -> 346646.97
A3: Operating cash flow | B3: 12474.745 | C3: 13347.977 | D3: 14148.856 | E3: 14856.299 | F3: 15599.114
A4: Capex | B4: 11088.662 | C4: 11864.869 | D4: 12576.761 | E4: 13205.599 | F4: 13865.879
A5: Free cash flow | B5: 1386.0828 | C5: 1483.1086 | D5: 1572.0951 | E5: 1650.6999 | F5: 1733.2349

Sheet 07_Forecast_BS (lite)

Sheet 08_Valuation_Bear
A1: WACC | B1: 0.13
A2: Terminal Growth Rate | B2: 0.025
A4: Year | B4: FY2026 | C4: FY2027 | D4: FY2028 | E4: FY2029 | F4: FY2030
A5: Free Cash Flow | B5: 4158.2484 | C5: 4449.3258 | D5: 4716.2853 | E5: 4952.0996 | F5: 5199.7046
A6: Year Number | B6: 1 | C6: 2 | D6: 3 | E6: 4 | F6: 5
A7: Discount Factor | B7: 0.88495575 | C7: 0.78314668 | D7: 0.69305016 | E7: 0.61331873 | F7: 0.54275994
A8: Present Value of FCF | B8: 3679.8658 | C8: 3484.4747 | D8: 3268.6223 | E8: 3037.2154 | F8: 2822.1913
A10: Terminal Value (FY2030) | F10: 50759.021
A11: PV of Terminal Value | F11: 27549.963
A13: Enterprise Value | B13: 43842.333
A15: Net Debt | B15: -2953
A16: Equity Value | B16: 46795.333
A17: Shares Outstanding (m) | B17: 591.34
A18: Implied Share Price (ZAR) | B18: 79.134394

Sheet 08_Valuation_Bull
A1: WACC | B1: 0.11
A2: Terminal Growth Rate | B2: 0.035
A4: Year | B4: FY2026 | C4: FY2027 | D4: FY2028 | E4: FY2029 | F4: FY2030
A5: Free Cash Flow | B5: 8870.9299 | C5: 9491.895 | D5: 10061.409 | E5: 10564.479 | F5: 11092.703
A6: Year Number | B6: 1 | C6: 2 | D6: 3 | E6: 4 | F6: 5
A7: Discount Factor | B7: 0.9009009 | C7: 0.81162243 | D7: 0.73119138 | E7: 0.65873097 | F7: 0.59345133
A8: Present Value of FCF | B8: 7991.8288 | C8: 7703.8349 | D8: 7356.8153 | E8: 6959.1496 | F8: 6582.9794
A10: Terminal Value (FY2030) | F10: 153079.3
A11: PV of Terminal Value | F11: 90845.116
A13: Enterprise Value | B13: 127439.72
A15: Net Debt | B15: -2953
A16: Equity Value | B16: 130392.72
A17: Shares Outstanding (m) | B17: 591.34
A18: Implied Share Price (ZAR) | B18: 220.50381

Sheet 08_Valuation_Base
A1: WACC | B1: ='02_Key_Assumptions_Base'!B14 -> 0.12
A2: Terminal Growth Rate | B2: ='02_Key_Assumptions_Base'!B15 -> 0.03
A4: Year | B4: FY2026 | C4: FY2027 | D4: FY2028 | E4: FY2029 | F4: FY2030
A5: Free Cash Flow | B5: 6930.414 | C5: 7415.543 | D5: 7860.4756 | E5: 8253.4993 | F5: 8666.1743
A6: Year Number | B6: 1 | C6: 2 | D6: 3 | E6: 4 | F6: 5
A7: Discount Factor | B7: 0.89285714 | C7: 0.79719388 | D7: 0.71178025 | E7: 0.63551808 | F7: 0.56742686
A8: Present Value of FCF | B8: 6187.8696 | C8: 5911.6255 | D8: 5594.9312 | E8: 5245.248 | F8: 4917.42
A10: Terminal Value (FY2030) | F10: 99179.55
A11: PV of Terminal Value | F11: 56277.14
A13: Enterprise Value | B13: 84134.235
A15: Net Debt | B15: -2953
A16: Equity Value | B16: 87087.235
A17: Shares Outstanding (m) | B17: 591.34
A18: Implied Share Price (ZAR) | B18: 147.271

Sheet 08_Valuation
A1: NOTE: This sheet is a DEPRECATED draft scenario (pre-separation of Bear/Base/Bull). Do not use for analysis. Refer to 08_Valuation_Base, 08_Valuation_Bull, 08_Valuation_Bear.
A3: WACC | B3: ='02_Key_Assumptions'!B14 -> 0.12
A4: Terminal Growth Rate | B4: Column1 | C4: Column2 | D4: Column3 | E4: Column4 | F4: Column5
A6: Year | B6: FY2026 | C6: FY2027 | D6: FY2028 | E6: FY2029 | F6: FY2030
A7: Free Cash Flow | B7: 1386.0828 | C7: 1483.1086 | D7: 1572.0951 | E7: 1650.6999 | F7: 1733.2349
A8: Year Number | B8: 1 | C8: 2 | D8: 3 | E8: 4 | F8: 5
A9: Discount Factor | B9: 0.89285714 | C9: 0.79719388 | D9: 0.71178025 | E9: 0.63551808 | F9: 0.56742686
A10: Present Value of FCF | B10: 1237.5739 | C10: 1182.3251 | D10: 1118.9862 | E10: 1049.0496 | F10: 983.48401
A12: Terminal Value (FY2030) | F12: 19835.91
A13: PV of Terminal Value | F13: 11255.428
A15: Enterprise Value | B15: 16826.847
A17: Net Debt | B17: -2953
A18: Equity Value | B18: 19779.847
A19: Shares Outstanding (m) | B19: 591.34
A20: Implied Share Price (ZAR) | B20: 33.449195

Sheet 09_Dashboard
A1: SHOPRITE HOLDINGS LIMITED — Discounted Cash Flow Valuation & Scenario Analysis
A2: Prepared by: Shawn Sibanyoni | Date: 19 February 2026 | Market Price: R264.00 | Source: Shoprite AFS FY2023–FY2025
L3: Implied Value (R) | M3: Market Price (R)
A4: Valuation Summary | F4: Key Assumptions Summary | K4: Bear | L4: 79.13 | M4: 264
A5: Scenario | B5: Implied Value (R) | C5: Market Price (R) | D5: (Discount) / Premium | F5: Assumption | G5: Bear | H5: Base | I5: Bull | K5: Base | L5: 147.27 | M5: 264
A6: Market Price | B6: R264,00 | C6: R264,00 | D6: — | F6: WACC | G6: 13,00% | H6: 12,00% | I6: 11,00% | K6: Bull | L6: 220.5 | M6: 264
A7: Bear Case | B7: R79,13 | C7: R264,00 | D7: -70,02% | F7: Terminal Growth | G7: 2,50% | H7: 3,00% | I7: 3,50%
A8: Base Case | B8: R147,27 | C8: R264,00 | D8: -44,22% | F8: OCF Margin | G8: 5,00% | H8: 5,50% | I8: 6,00%
A9: Bull Case | B9: R220,50 | C9: R264,00 | D9: -16,48% | F9: Capex % of Revenue | G9: 3,50% | H9: 3,00% | I9: 2,80%
F10: FCF Margin (derived) | G10: 0.015 | H10: 0.025 | I10: 0.032
A12: Scenario Comparison — Implied Value vs Market Price | F12: Historical FCF
B13: Implied Value (R) | C13: Market Price (R) | D13: Upside / (Downside) | F13: Metric | G13: FY2023 | H13: FY2024 | I13: FY2025
A14: Bear | B14: R79,13 | C14: R264,00 | D14: -70,02% | F14: Operating CF (Rm) | G14: 9 831 | H14: 13 841 | I14: 10 984
A15: Base | B15: R147,27 | C15: R264,00 | D15: -44,22% | F15: Capex (Rm) | G15: 6 229 | H15: 6 779 | I15: 7 365
A16: Bull | B16: R220,50 | C16: R264,00 | D16: -16,48% | F16: Free CF (Rm) | G16: 3 602 | H16: 7 062 | I16: 3 619
F17: OCF Margin % | G17: 4,5% | H17: 5,6% | I17: 4,3%
F18: FCF Margin % | G18: 1,6% | H18: 2,9% | I18: 1,4%
F19: FCF Conv. (×PAT) | G19: 0,57x | H19: 1,08x | I19: 0,49x

Sheet 10_Investment_Summary
A1: SHOPRITE HOLDINGS
A2: Investment Summary – DCF Valuation
A5: Metric | B5: Value
A6: Current Market Price | B6: 264
A7: Base Case Intrinsic Value | B7: 147.27
A8: Bear Case Value | B8: 79.13
A9: Bull Case Value | B9: 220.5
A10: Implied Upside / (Downside) – Base | B10: -0.44215529
A14: Investment View
A16: A discounted cash flow analysis indicates that Shoprite’s intrinsic value ranges between R79.13 and R220.50 per share across bear and bull scenarios. The base case valuation of R147.27 implies a downside of approximately 44% relative to the current market price of R264.00. Even under more optimistic operating assumptions, the valuation does not exceed the prevailing market price, suggesting that the stock is currently trading above fundamental value estimates derived from projected cash flows.
A19: Key Valuation Drivers
A21: Discount rate (WACC range: 11%–13%) Terminal growth assumption (2.5%–3.5%) Operating cash flow margin (5%–6%) Capex intensity (2.8%–3.5%)
A23: Risks to The View
A25: Structural improvement in margins above modeled range Lower cost of capital due to macro stabilization Stronger-than-expected free cash flow growth Multiple expansion driven by sentiment
A28: Closing Statement
A30: This valuation exercise demonstrates the application of fundamental discounted cash flow methodology to assess intrinsic equity value under varying macroeconomic and operational assumptions. While market pricing may reflect sentiment, momentum, and forward expectations beyond modeled inputs, the analysis provides a structured framework for evaluating valuation risk and return asymmetry. Based on projected free cash flows, cost of capital assumptions, and terminal growth parameters, the current market price appears to embed expectations materially above base-case intrinsic value estimates. The model therefore suggests limited margin of safety at present levels, reinforcing the importance of disciplined capital allocation and scenario-based risk assessment.
