Workbook

Sheet 00_control
A1: Reporting Currency | B1: ZAR
A2: Units | B2: R million
A4: Financial Years | B4: FY2023 | C4: FY2024 | D4: FY2025

Sheet 01_Raw_IS
A1: Line Item | B1: FY2023 | C1: FY2024 | D1: FY2025
A2: Revenue | B2: 219530 | C2: 246082 | D2: 256682
A3: Sale of merchandise | B3: 214956 | C3: 240718 | D3: 252701
A4: Cost of sales | B4: 163250 | C4: 182968 | D4: 191259
A5: Gross profit | B5: 51706 | C5: 57750 | D5: 61442
A6: Operating profit | B6: 12344 | C6: 13156 | D6: 14943
A7: Net finance costs | B7: 3665 | C7: 4306 | D7: 5115
A8: Profit before tax | B8: 9132 | C8: 9379 | D8: 10185
A9: Income tax expense | B9: 2812 | C9: 2836 | D9: 2793
A10: Profit after tax | B10: 5901 | C10: 6221 | D10: 7583

Sheet 02_Raw_BS
A1: Line Item | B1: FY2023 | C1: FY2024 | D1: FY2025
A2: Total assets | B2: 102356 | C2: 112328 | D2: 124944
A3: Current assets | B3: 47871 | C3: 50059 | D3: 52867
A4: Cash and cash equivalents | B4: 12548 | C4: 11732 | D4: 9946
A5: Inventory | B5: 25090 | C5: 28366 | D5: 29748
A6: Total equity | B6: 26278 | C6: 27724 | D6: 30117
A7: Total liabilities | B7: 76078 | C7: 84604 | D7: 94827
A8: Current liabilities | B8: 37416 | C8: 41538 | D8: 44541
A9: Interest-bearing borrowings | B9: 6368 | C9: 5993 | D9: 6993

Sheet 03_Raw_CF
A1: Line Item | B1: FY2023 | C1: FY2024 | D1: FY2025
A2: Net cash from operating activities | B2: 9831 | C2: 13841 | D2: 10984
A3: Net cash used in investing activities | B3: 6229 | C3: 6779 | D3: 7365
A4: Net cash from financing activities | B4: 2855 | C4: 4012 | D4: 4298
A5: Net increase / (decrease) in cash | B5: 747 | C5: 3050 | D5: 679

Sheet 04_Clean_IS
A1: Line Item | B1: FY2023 | C1: FY2024 | D1: FY2025
A2: Revenue | B2: ='01_Raw_IS'!B2 -> 219530 | C2: ='01_Raw_IS'!C2 -> 246082 | D2: ='01_Raw_IS'!D2 -> 256682
A3: Sale of merchandise | B3: ='01_Raw_IS'!B3 -> 214956 | C3: ='01_Raw_IS'!C3 -> 240718 | D3: ='01_Raw_IS'!D3 -> 252701
A4: Cost of sales | B4: ='01_Raw_IS'!B4 -> 163250 | C4: ='01_Raw_IS'!C4 -> 182968 | D4: ='01_Raw_IS'!D4 -> 191259
A5: Gross profit | B5: =B3-B4 -> 51706 | C5: =C3-C4 -> 57750 | D5: =D3-D4 -> 61442
A6: Gross margin % | B6: =B5/B3 -> 0.24054225 | C6: =C5/C3 -> 0.23990728 | D6: =D5/D3 -> 0.2431411
A7: Operating profit | B7: ='01_Raw_IS'!B6 -> 12344 | C7: ='01_Raw_IS'!C6 -> 13156 | D7: ='01_Raw_IS'!D6 -> 14943
A8: Operating margin % | B8: =B7/B2 -> 0.056229217 | C8: =C7/C2 -> 0.053461854 | D8: =D7/D2 -> 0.058216003
A9: Finance costs | B9: ='01_Raw_IS'!B7 -> 3665 | C9: ='01_Raw_IS'!C7 -> 4306 | D9: ='01_Raw_IS'!D7 -> 5115
A10: Interest received | B10: 453 | C10: 529 | D10: 357
A11: Profit before tax | B11: =B7-(B9-B10) -> 9132 | C11: =C7-(C9-C10) -> 9379 | D11: =D7-(D9-D10) -> 10185
A12: Income tax expense | B12: ='01_Raw_IS'!B9 -> 2812 | C12: ='01_Raw_IS'!C9 -> 2836 | D12: ='01_Raw_IS'!D9 -> 2793
A13: Profit after tax | B13: =B11-B12 -> 6320 | C13: =C11-C12 -> 6543 | D13: =D11-D12 -> 7392
A14: Net margin % | B14: =B13/B2 -> 0.028788776 | C14: =C13/C2 -> 0.026588698 | D14: =D13/D2 -> 0.02879828

Sheet 05_Clean_BS
A1: Line Item | B1: FY2023 | C1: FY2024 | D1: FY2025
A2: Current assets
A3: Cash and cash equivalents | B3: ='02_Raw_BS'!B4 -> 12548 | C3: ='02_Raw_BS'!C4 -> 11732 | D3: ='02_Raw_BS'!D4 -> 9946
A4: Trade and other receivables
A5: Inventories | B5: ='02_Raw_BS'!B5 -> 25090 | C5: ='02_Raw_BS'!C5 -> 28366 | D5: ='02_Raw_BS'!D5 -> 29748
A6: Other current assets
A7: Total current assets | B7: ='02_Raw_BS'!B3 -> 47871 | C7: ='02_Raw_BS'!C3 -> 50059 | D7: ='02_Raw_BS'!D3 -> 52867
A8: Non-current assets
A9: Property, plant and equipment
A10: Right-of-use assets
A11: Intangible assets
A12: Investments in associates
A13: Other non-current assets
A14: Total non-current assets | B14: ='02_Raw_BS'!B2-B7 -> 54485 | C14: ='02_Raw_BS'!C2 - C7 -> 62269 | D14: ='02_Raw_BS'!D2 - D7 -> 72077
A15: Total assets | B15: ='02_Raw_BS'!B2 -> 102356 | C15: ='02_Raw_BS'!C2 -> 112328 | D15: ='02_Raw_BS'!D2 -> 124944
A16: Equity
A17: Share capital
A18: Retained earnings
A19: Other reserves
A20: Total equity | B20: ='02_Raw_BS'!B6 -> 26278 | C20: ='02_Raw_BS'!C6 -> 27724 | D20: ='02_Raw_BS'!D6 -> 30117
A21: Current liabilities
A22: Trade and other payables
A23: Borrowings (current)
A24: Lease liabilities (current)
A25: Provisions
A26: Other current liabilities
A27: Total current liabilities | B27: ='02_Raw_BS'!B8 -> 37416 | C27: ='02_Raw_BS'!C8 -> 41538 | D27: ='02_Raw_BS'!D8 -> 44541
A28: Non-current liabilities
A29: Borrowings (non-current)
A30: Lease liabilities (non-current)
A31: Deferred tax liabilities
A32: Other non-current liabilities
A33: Total non-current liabilities | B33: ='02_Raw_BS'!B7 - B27 -> 38662 | C33: ='02_Raw_BS'!C7 - C27 -> 43066 | D33: ='02_Raw_BS'!D7 - D27 -> 50286
A34: Total liabilities | B34: ='02_Raw_BS'!B7 -> 76078 | C34: ='02_Raw_BS'!C7 -> 84604 | D34: ='02_Raw_BS'!D7 -> 94827
A35: Total equity and liabilities | B35: =B20 + B34 -> 102356 | C35: =C20 + C34 -> 112328 | D35: =D20 + D34 -> 124944

Sheet 06_Clean_CF
A1: Line Item | B1: FY2023 | C1: FY2024 | D1: FY2025
A2: Cash flows from operating activities
A3: Cash generated from operations
A4: Net working capital changes
A5: Cash generated from operations before tax
A6: Income tax paid
A7: Net cash from operating activities | B7: ='03_Raw_CF'!B2 -> 9831 | C7: ='03_Raw_CF'!C2 -> 13841 | D7: ='03_Raw_CF'!D2 -> 10984
A8: Cash flows from investing activities
A9: Capital expenditure | B9: 6229 | C9: 6779 | D9: 7365
A10: Other investing activities
A11: Net cash used in investing activities | B11: ='03_Raw_CF'!B3 -> 6229 | C11: ='03_Raw_CF'!C3 -> 6779 | D11: ='03_Raw_CF'!D3 -> 7365
A12: Cash flows from financing activities
A13: Proceeds from borrowings
A14: Repayment of borrowings
A15: Dividends paid
A16: Other financing activities
A17: Net cash from financing activities | B17: ='03_Raw_CF'!B4 -> 2855 | C17: ='03_Raw_CF'!C4 -> 4012 | D17: ='03_Raw_CF'!D4 -> 4298
A18: Net change in cash | B18: ='03_Raw_CF'!B5 -> 747 | C18: ='03_Raw_CF'!C5 -> 3050 | D18: ='03_Raw_CF'!D5 -> 679
A19: Opening cash balance | B19: =B20-B18 -> 11801 | C19: =C20-C18 -> 8682 | D19: =D20-D18 -> 9267
A20: Closing cash balance | B20: ='02_Raw_BS'!B4 -> 12548 | C20: ='02_Raw_BS'!C4 -> 11732 | D20: ='02_Raw_BS'!D4 -> 9946

Sheet 07_Ratios
A1: Ratio | B1: FY2023 | C1: FY2024 | D1: FY2025
A2: Gross margin % | B2: ='04_Clean_IS'!B6 -> 0.24054225 | C2: ='04_Clean_IS'!C6 -> 0.23990728 | D2: ='04_Clean_IS'!D6 -> 0.2431411
A3: Operating margin % | B3: ='04_Clean_IS'!B8 -> 0.056229217 | C3: ='04_Clean_IS'!C8 -> 0.053461854 | D3: ='04_Clean_IS'!D8 -> 0.058216003
A4: Net margin % | B4: ='04_Clean_IS'!B14 -> 0.028788776 | C4: ='04_Clean_IS'!C14 -> 0.026588698 | D4: ='04_Clean_IS'!D14 -> 0.02879828
A6: Return on assets (ROA) | B6: ='04_Clean_IS'!B13 / '05_Clean_BS'!B15 -> 0.061745281 | C6: ='04_Clean_IS'!C13 / '05_Clean_BS'!C15 -> 0.058249056 | D6: ='04_Clean_IS'!D13 / '05_Clean_BS'!D15 -> 0.059162505
A7: Return on equity (ROE) | B7: ='04_Clean_IS'!B13 / '05_Clean_BS'!B20 -> 0.24050537 | C7: ='04_Clean_IS'!C13 / '05_Clean_BS'!C20 -> 0.23600491 | D7: ='04_Clean_IS'!D13 / '05_Clean_BS'!D20 -> 0.24544277
A9: Current ratio | B9: ='05_Clean_BS'!B7 / '05_Clean_BS'!B27 -> 1.2794259 | C9: ='05_Clean_BS'!C7 / '05_Clean_BS'!C27 -> 1.2051375 | D9: ='05_Clean_BS'!D7 / '05_Clean_BS'!D27 -> 1.1869289
A10: Cash ratio | B10: ='05_Clean_BS'!B3 / '05_Clean_BS'!B27 -> 0.33536455 | C10: ='05_Clean_BS'!C3 / '05_Clean_BS'!C27 -> 0.28244018 | D10: ='05_Clean_BS'!D3 / '05_Clean_BS'!D27 -> 0.22329988
A12: Debt to equity | B12: ='05_Clean_BS'!B34 / '05_Clean_BS'!B20 -> 2.8951214 | C12: ='05_Clean_BS'!C34 / '05_Clean_BS'!C20 -> 3.051652 | D12: ='05_Clean_BS'!D34 / '05_Clean_BS'!D20 -> 3.1486204
A13: Debt to assets | B13: ='05_Clean_BS'!B34 / '05_Clean_BS'!B15 -> 0.74326859 | C13: ='05_Clean_BS'!C34 / '05_Clean_BS'!C15 -> 0.75318709 | D13: ='05_Clean_BS'!D34 / '05_Clean_BS'!D15 -> 0.75895601
A15: Operating cash flow margin | B15: ='06_Clean_CF'!B7 / '04_Clean_IS'!B2 -> 0.044782034 | C15: ='06_Clean_CF'!C7 / '04_Clean_IS'!C2 -> 0.056245479 | D15: ='06_Clean_CF'!D7 / '04_Clean_IS'!D2 -> 0.042792249
A16: Cash conversion (OCF / PAT) | B16: ='06_Clean_CF'!B7 / '04_Clean_IS'!B13 -> 1.555538 | C16: ='06_Clean_CF'!C7 / '04_Clean_IS'!C13 -> 2.1153905 | D16: ='06_Clean_CF'!D7 / '04_Clean_IS'!D13 -> 1.4859307
A18: Free cash flow (Rm) | B18: 3602 | C18: 7062 | D18: 3619
A19: FCF margin % | B19: 0.01640778 | C19: 0.028697751 | D19: 0.014099158
A20: FCF conversion (FCF / PAT) | B20: 0.56993671 | C20: 1.0793214 | D20: 0.48958333

Sheet 08_Trends
A1: Metric | B1: FY2023 | C1: FY2024 | D1: FY2025 | E1: YoY % (23 → 24) | F1: YoY % (24 → 25)
A2: Revenue | B2: ='04_Clean_IS'!B2 -> 219530 | C2: ='04_Clean_IS'!C2 -> 246082 | D2: ='04_Clean_IS'!D2 -> 256682 | E2: =(C2/B2)-1 -> 0.1209493 | F2: =(D2/C2)-1 -> 0.043075073
A3: Gross profit | B3: ='04_Clean_IS'!B5 -> 51706 | C3: ='04_Clean_IS'!C5 -> 57750 | D3: ='04_Clean_IS'!D5 -> 61442 | E3: =(C3/B3)-1 -> 0.11689166 | F3: =(D3/C3)-1 -> 0.063930736
A4: Operating profit | B4: ='04_Clean_IS'!B7 -> 12344 | C4: ='04_Clean_IS'!C7 -> 13156 | D4: ='04_Clean_IS'!D7 -> 14943 | E4: =(C4/B4)-1 -> 0.065780946 | F4: =(D4/C4)-1 -> 0.13583156
A5: Profit after tax | B5: ='04_Clean_IS'!B13 -> 6320 | C5: ='04_Clean_IS'!C13 -> 6543 | D5: ='04_Clean_IS'!D13 -> 7392 | E5: =(C5/B5)-1 -> 0.03528481 | F5: =(D5/C5)-1 -> 0.12975699
A6: Gross margin % | B6: ='04_Clean_IS'!B6 -> 0.24054225 | C6: ='04_Clean_IS'!C6 -> 0.23990728 | D6: ='04_Clean_IS'!D6 -> 0.2431411 | E6: =(C6/B6)-1 -> -0.0026397571 | F6: =(D6/C6)-1 -> 0.013479483
A7: Operating margin % | B7: ='04_Clean_IS'!B8 -> 0.056229217 | C7: ='04_Clean_IS'!C8 -> 0.053461854 | D7: ='04_Clean_IS'!D8 -> 0.058216003 | E7: =(C7/B7)-1 -> -0.049215745 | F7: =(D7/C7)-1 -> 0.088925994
A8: Net margin % | B8: ='04_Clean_IS'!B14 -> 0.028788776 | C8: ='04_Clean_IS'!C14 -> 0.026588698 | D8: ='04_Clean_IS'!D14 -> 0.02879828 | E8: =(C8/B8)-1 -> -0.076421378 | F8: =(D8/C8)-1 -> 0.083102283
A10: Total assets | B10: ='05_Clean_BS'!B15 -> 102356 | C10: ='05_Clean_BS'!C15 -> 112328 | D10: ='05_Clean_BS'!D15 -> 124944 | E10: =(C10/B10)-1 -> 0.097424675 | F10: =(D10/C10)-1 -> 0.11231394
A11: Total equity | B11: ='05_Clean_BS'!B20 -> 26278 | C11: ='05_Clean_BS'!C20 -> 27724 | D11: ='05_Clean_BS'!D20 -> 30117 | E11: =(C11/B11)-1 -> 0.055027019 | F11: =(D11/C11)-1 -> 0.086315106
A12: Total liabilities | B12: ='05_Clean_BS'!B34 -> 76078 | C12: ='05_Clean_BS'!C34 -> 84604 | D12: ='05_Clean_BS'!D34 -> 94827 | E12: =(C12/B12)-1 -> 0.11206919 | F12: =(D12/C12)-1 -> 0.12083353
A14: Operating cash flow | B14: ='06_Clean_CF'!B7 -> 9831 | C14: ='06_Clean_CF'!C7 -> 13841 | D14: ='06_Clean_CF'!D7 -> 10984 | E14: =(C14/B14)-1 -> 0.4078934 | F14: =(D14/C14)-1 -> -0.20641572
A15: Capital expenditure | B15: 6229 | C15: 6779 | D15: 7365 | E15: 0.088296677 | F15: 0.086443428
A16: Free cash flow | B16: 3602 | C16: 7062 | D16: 3619 | E16: 0.96057746 | F16: -0.48753894
A18: ROA | B18: ='07_Ratios'!B6 -> 0.061745281 | C18: ='07_Ratios'!C6 -> 0.058249056 | D18: ='07_Ratios'!D6 -> 0.059162505 | E18: =(C18/B18)-1 -> -0.056623353 | F18: =(D18/C18)-1 -> 0.015681773
A19: ROE | B19: ='07_Ratios'!B7 -> 0.24050537 | C19: ='07_Ratios'!C7 -> 0.23600491 | D19: ='07_Ratios'!D7 -> 0.24544277 | E19: =(C19/B19)-1 -> -0.018712515 | F19: =(D19/C19)-1 -> 0.039990134
A20: Current ratio | B20: ='07_Ratios'!B9 -> 1.2794259 | C20: ='07_Ratios'!C9 -> 1.2051375 | D20: ='07_Ratios'!D9 -> 1.1869289 | E20: =(C20/B20)-1 -> -0.058063893 | F20: =(D20/C20)-1 -> -0.015109121
A21: Debt to equity | B21: ='07_Ratios'!B12 -> 2.8951214 | C21: ='07_Ratios'!C12 -> 3.051652 | D21: ='07_Ratios'!D12 -> 3.1486204 | E21: =(C21/B21)-1 -> 0.054067026 | F21: =(D21/C21)-1 -> 0.031775701
A22: Operating cash flow margin | B22: ='07_Ratios'!B15 -> 0.044782034 | C22: ='07_Ratios'!C15 -> 0.056245479 | D22: ='07_Ratios'!D15 -> 0.042792249 | E22: =(C22/B22)-1 -> 0.25598312 | F22: =(D22/C22)-1 -> -0.23918776

Sheet 09_Dashboard
A1: SHOPRITE HOLDINGS LIMITED — Financial Performance Dashboard FY2023–FY2025
A2: Prepared by: Shawn Sibanyoni | Date: 19 February 2026 | Source: Shoprite Holdings AFS FY2023–FY2025
A4: Revenue (FY2025) | C4: Operating Margin (FY2025) | E4: ROE (FY2025) | G4: FCF (FY2025) | I4: FCF Margin (FY2025) | K4: Current Ratio (FY2025)
A5: R256,682m | C5: 5.8% | E5: 24.5% | G5: R3,619m | I5: 1.4% | K5: 1.19x
A8: Income Statement Summary (Rm)
A9: Metric | B9: FY2023 | C9: FY2024 | D9: FY2025
A10: Revenue | B10: 219530 | C10: 246082 | D10: 256682
A11: Gross Profit | B11: 52249 | C11: 59327 | D11: 62376
A12: Gross Margin % | B12: 0.238 | C12: 0.241 | D12: 0.243
A13: Operating Profit | B13: 12344 | C13: 14210 | D13: 14943
A14: Operating Margin % | B14: 0.0562 | C14: 0.0578 | D14: 0.0582
A15: Profit After Tax | B15: 6320 | C15: 6543 | D15: 7392
A16: Net Margin % | B16: 0.0288 | C16: 0.0266 | D16: 0.0288
A19: Cash Flow Summary (Rm) — Key Correction
A20: Metric | B20: FY2023 | C20: FY2024 | D20: FY2025
A21: Operating Cash Flow | B21: 9831 | C21: 13841 | D21: 10984
A22: Capital Expenditure | B22: 6229 | C22: 6779 | D22: 7365
A23: Free Cash Flow | B23: 3602 | C23: 7062 | D23: 3619
A24: OCF Margin % | B24: 0.0448 | C24: 0.0563 | D24: 0.0428
A25: FCF Margin % | B25: 0.0164 | C25: 0.0287 | D25: 0.0141
A26: FCF Conversion (FCF/PAT) | B26: 0.57 | C26: 1.079 | D26: 0.49
A27: Cash Conversion (OCF/PAT) | B27: 1.556 | C27: 2.116 | D27: 1.486
A29: Note: FCF = OCF less Capex (net investing activities). Capex sourced from Shoprite AFS investing section. FCF ≠ OCF — previous versions incorrectly equated the two.
A31: Balance Sheet Summary (Rm)
A32: Metric | B32: FY2023 | C32: FY2024 | D32: FY2025
A33: Total Assets | B33: 102356 | C33: 112840 | D33: 124944
A34: Total Equity | B34: 26278 | C34: 27893 | D34: 30117
A35: Total Liabilities | B35: 76078 | C35: 84947 | D35: 94827
A36: Current Ratio | B36: 1.28 | C36: 1.23 | D36: 1.19
A37: Debt-to-Equity | B37: 2.9 | C37: 3.04 | D37: 3.15
A38: ROE % | B38: 0.2405 | C38: 0.2346 | D38: 0.2455

Sheet 10_Executive_Memo
A1: Executive Memo — Shoprite Holdings (FY2023–FY2025)
A2: Purpose: Summarise performance trends and highlight key drivers / risks
A3: Prepared by: Saun Sibanyoni | Date: 10 February 2026
A5: KPI | B5: FY2023 | C5: FY2024 | D5: FY2025
A6: Revenue (Rm) | B6: ='08_Trends'!B2 -> 219530 | C6: ='08_Trends'!C2 -> 246082 | D6: ='08_Trends'!D2 -> 256682
A7: Operating profit (Rm) | B7: ='08_Trends'!B4 -> 12344 | C7: ='08_Trends'!C4 -> 13156 | D7: ='08_Trends'!D4 -> 14943
A8: Profit after tax (Rm) | B8: ='08_Trends'!B5 -> 6320 | C8: ='08_Trends'!C5 -> 6543 | D8: ='08_Trends'!D5 -> 7392
A9: Operating margin % | B9: ='08_Trends'!B7 -> 0.056229217 | C9: ='08_Trends'!C7 -> 0.053461854 | D9: ='08_Trends'!D7 -> 0.058216003
A10: ROE % | B10: ='08_Trends'!B19 -> 0.24050537 | C10: ='08_Trends'!C19 -> 0.23600491 | D10: ='08_Trends'!D19 -> 0.24544277
A11: Operating cash flow | B11: ='08_Trends'!B14 -> 9831 | C11: ='08_Trends'!C14 -> 13841 | D11: ='08_Trends'!D14 -> 10984
A13: Executive Summary (FY2023-FY2025)
A15: Shoprite delivered consistent top-line growth over FY2023-FY2025, with revenue increasing from R219,530m to R256,682m. While revenue growth moderated in FY2025 relative to FY2024, overall profitability remained resilient. Operating margins were maintained in the mid-5% range, and net margins remained broadly stable, reflecting disciplined cost control in a challenging retail environment.
A17: Revenue & Profitability Revenue growth decelerated from FY2024 to FY2025, consistent with scale effects as the business matures. Despite this moderation, gross margins remained stable in the low-to-mid 24% range, indicating effective pricing and cost management. Operating profit increased from R12,344m in FY2023 to R14,943m in FY2025, supported by steady operating margin performance. Profit after tax rose from R6,320m to R7,392m, with net margins holding around ~3% and showing a modest recovery in FY2025. Overall, profitability trends suggest a business transitioning from high-growth expansion toward efficiency, margin protection, and operational discipline.
A19: Cash Flow & Earnings Quality Operating cash flow strengthened significantly in FY2024, reaching R13,841m, before normalising to R10,984m in FY2025. This pattern indicates timing effects related to working capital movements, which are typical in large-scale retail operations. Operating cash flow margin peaked in FY2024 before declining in FY2025, highlighting cash conversion volatility as a key variable. While earnings quality remains acceptable, sustained consistency between profit and cash generation warrants ongoing monitoring, particularly across inventory and supplier payment cycles.
A21: Balance Sheet & Financial Position Total assets expanded from R102,356m to R124,944m over the period, reflecting continued investment in the operating base. Total liabilities increased in parallel from R76,078m to R94,827m. Liquidity tightened gradually, with the current ratio declining from 1.28 to 1.19, while leverage increased moderately, with debt-to-equity rising from 2.90 to 3.15. Although these movements are not immediately concerning, they indicate a reduced liquidity buffer and a higher reliance on efficient working capital management and cash flow discipline.
A23: Key Takeaways / Watch Items - Growth remains healthy but is moderating, shifting management focus from expansion toward productivity, efficiency, and margin preservation. - Margins are stable, suggesting strong cost control; however, sustainability should be assessed against inflationary pressures and competitive pricing dynamics. - Cash conversion volatility is the primary swing factor, requiring deeper analysis of working capital drivers. - Leverage and liquidity are tightening, reinforcing the importance of disciplined capital allocation and balance sheet management.
A25: Key Risks - Working capital pressure and variability in cash conversion - Margin compression from input cost inflation or heightened price competition - Gradual tightening of liquidity as leverage increases
A27: Next Analysis Priorities - Detailed working capital analysis (inventory, payables, receivables days) - Store-level or segment productivity analysis (subject to data availability) - Interest coverage and lease liability sensitivity analysis, given retail exposure

Sheet 99_Definitions
A1: Definitions & Methodology Notes
A3: Free Cash Flow (FCF) | B3: Net Cash from Operating Activities minus Capital Expenditure (Net Investing Activities). Capex sourced from investing activities section of Shoprite AFS.
A4: Return on Equity (ROE) | B4: Profit After Tax / Total Equity. Note: PAT used (not headline earnings) for consistency with reported PAT. For SA comparisons, headline earnings ROE may differ marginally.
A5: Return on Assets (ROA) | B5: Profit After Tax / Total Assets
A6: Operating Cash Flow Margin | B6: Net Cash from Operating Activities / Revenue
A7: Cash Conversion (OCF / PAT) | B7: Measures quality of earnings — how much of reported profit converts to operating cash flow
A8: FCF Margin | B8: Free Cash Flow / Revenue
A9: Capital Expenditure | B9: Sourced from Net Cash Used in Investing Activities (Shoprite AFS). Represents primarily growth and maintenance capex.
