Workbook

Sheet README
A3: Naspers Ltd – Integrated Holding Company & SOTP Framework
A4: Time Horizon: FY2020-FY2025
A6: Objective:
A8: To evaluate intrinsic value, structural discount persistence, and capital allocation discipline using a look-through NAV and SOTP framework.
A10: Structural Note — Prosus Intermediary
A11: Since the 2019 Prosus restructuring, Naspers does not hold Tencent directly. Naspers holds ~57% of Prosus N.V. (listed Amsterdam), which holds ~24% of Tencent (as of 2025). The effective economic interest (Naspers % × Prosus Tencent %) is captured in the ownership % column in tbl_nav_components. Pre-2019 figures reflect a more direct structure. This model uses the effective interest approach consistently across the time series.

Sheet tbl_price_history
A3: tbl_naspers_price
A5: Date | B5: Share Price (ZAR) | C5: Shares Outstanding (B) | D5: Market Cap (ZAR B)
A6: 43220 | B6: 384.62 | C6: 2.14 | D6: =B6*C6 -> 823.0868
A7: =EOMONTH(A6,1) -> 43251 | B7: 380.41 | C7: 2.14 | D7: =B7*C7 -> 814.0774
A8: =EOMONTH(A7,1) -> 43281 | B8: 438.12 | C8: 2.14 | D8: =B8*C8 -> 937.5768
A9: =EOMONTH(A8,1) -> 43312 | B9: 407.57 | C9: 2.14 | D9: =B9*C9 -> 872.1998
A10: =EOMONTH(A9,1) -> 43343 | B10: 410.56 | C10: 2.14 | D10: =B10*C10 -> 878.5984
A11: =EOMONTH(A10,1) -> 43373 | B11: 383.64 | C11: 2.14 | D11: =B11*C11 -> 820.9896
A12: =EOMONTH(A11,1) -> 43404 | B12: 325.95 | C12: 2.14 | D12: =B12*C12 -> 697.533
A13: =EOMONTH(A12,1) -> 43434 | B13: 347.36 | C13: 2.14 | D13: =B13*C13 -> 743.3504
A14: =EOMONTH(A13,1) -> 43465 | B14: 363.61 | C14: 2.14 | D14: =B14*C14 -> 778.1254
A15: =EOMONTH(A14,1) -> 43496 | B15: 382.19 | C15: 2.14 | D15: =B15*C15 -> 817.8866
A16: =EOMONTH(A15,1) -> 43524 | B16: 394.87 | C16: 2.14 | D16: =B16*C16 -> 845.0218
A17: =EOMONTH(A16,1) -> 43555 | B17: 432.05 | C17: 2.14 | D17: =B17*C17 -> 924.587
A18: =EOMONTH(A17,1) -> 43585 | B18: 473.92 | C18: 2.14 | D18: =B18*C18 -> 1014.1888
... A89: =EOMONTH(A88,1) -> 45747 | B89: 903.56 | C89: 0.932 | D89: =B89*C89 -> 842.11792

Sheet tbl_tencent_market
A3: tbl_tencent_market
A5: Date | B5: Tencent Price (HKD) | C5: Shares Outstanding (B) | D5: Market Cap (HKD B)
A6: =tbl_price_history!A6 -> 43220 | B6: 346.11 | C6: 9.081 | D6: =B6*C6 -> 3143.0249
A7: =tbl_price_history!A7 -> 43251 | B7: 353.36 | C7: 9.081 | D7: =B7*C7 -> 3208.8622
A8: =tbl_price_history!A8 -> 43281 | B8: 349.4 | C8: 9.081 | D8: =B8*C8 -> 3172.9014
A9: =tbl_price_history!A9 -> 43312 | B9: 315.15 | C9: 9.081 | D9: =B9*C9 -> 2861.8771
A10: =tbl_price_history!A10 -> 43343 | B10: 301.66 | C10: 9.081 | D10: =B10*C10 -> 2739.3745
A11: =tbl_price_history!A11 -> 43373 | B11: 286.76 | C11: 9.081 | D11: =B11*C11 -> 2604.0676
A12: =tbl_price_history!A12 -> 43404 | B12: 236.89 | C12: 9.081 | D12: =B12*C12 -> 2151.1981
A13: =tbl_price_history!A13 -> 43434 | B13: 276.82 | C13: 9.081 | D13: =B13*C13 -> 2513.8024
A14: =tbl_price_history!A14 -> 43465 | B14: 278.59 | C14: 9.081 | D14: =B14*C14 -> 2529.8758
A15: =tbl_price_history!A15 -> 43496 | B15: 306.99 | C15: 9.081 | D15: =B15*C15 -> 2787.7762
A16: =tbl_price_history!A16 -> 43524 | B16: 297.94 | C16: 9.081 | D16: =B16*C16 -> 2705.5931
A17: =tbl_price_history!A17 -> 43555 | B17: 320.29 | C17: 9.081 | D17: =B17*C17 -> 2908.5535
... A89: =tbl_price_history!A89 -> 45747 | B89: 492.7 | C89: 9.081 | D89: =B89*C89 -> 4474.2087

Sheet tbl_fx_rates
A3: tbl_fx_rates
A5: Date | B5: HKD_ZAR | C5: USD_ZAR
A6: =tbl_price_history!A6 -> 43220 | B6: 1.59 | C6: 12.46
A7: =tbl_price_history!A7 -> 43251 | B7: 1.62 | C7: 12.7
A8: =tbl_price_history!A8 -> 43281 | B8: 1.75 | C8: 13.72
A9: =tbl_price_history!A9 -> 43312 | B9: 1.69 | C9: 13.27
A10: =tbl_price_history!A10 -> 43343 | B10: 1.87 | C10: 14.68
A11: =tbl_price_history!A11 -> 43373 | B11: 1.81 | C11: 14.14
A12: =tbl_price_history!A12 -> 43404 | B12: 1.89 | C12: 14.78
A13: =tbl_price_history!A13 -> 43434 | B13: 1.77 | C13: 13.86
A14: =tbl_price_history!A14 -> 43465 | B14: 1.83 | C14: 14.35
A15: =tbl_price_history!A15 -> 43496 | B15: 1.69 | C15: 13.25
A16: =tbl_price_history!A16 -> 43524 | B16: 1.79 | C16: 14.08
A17: =tbl_price_history!A17 -> 43555 | B17: 1.84 | C17: 14.48
... A89: =tbl_price_history!A89 -> 45747 | B89: 2.35 | C89: 18.31

Sheet calc_lookthrough_nav
A3: calc_lookthrough_nav
A5: Date | B5: TCE_MktCap_HKD_B | C5: HKD_ZAR | D5: Fiscal_Year | E5: TCE_MktCap_ZAR_B | F5: Ownership_% | G5: Naspers_TCE_Value_ZAR_B | H5: Net_debt_USD_B | I5: USD_ZAR | J5: Net_Debt_ZAR_B | K5: NAV_ZAR_B | L5: Naspers_MktCap_ZAR_B | M5: NAV_Discount_% | N5: Discount_ZAR_B
A6: =tbl_price_history!A6 -> 43220 | B6: =_xlfn.XLOOKUP(A6,tbl_tencent_market_data[Date],tbl_tencent_market_data[Market Cap (HKD B)]) -> 3143.0249 | C6: =_xlfn.XLOOKUP(A6,tbl_fx_rates_data[Date],tbl_fx_rates_data[HKD_ZAR]) -> 1.59 | D6: =YEAR(EDATE(A6,9)) -> 2019 | E6: =B6*C6 -> 4997.4096 | F6: =_xlfn.XLOOKUP(D6,tbl_ownership[Fiscal_Year],tbl_ownership[Ownership_%]) -> 0.31 | G6: =E6*F6 -> 1549.197 | H6: =_xlfn.XLOOKUP(D6,tbl_netdebt[Fiscal_Year],tbl_netdebt[Net_debt_USD_B],0) -> -9.1 | I6: =_xlfn.XLOOKUP(A6,tbl_fx_rates_data[Date],tbl_fx_rates_data[USD_ZAR]) -> 12.46 | J6: =H6*I6 -> -113.386 | K6: =G6-J6 -> 1662.583 | L6: =_xlfn.XLOOKUP(Table6[[#This Row],[Date]],tbl_naspers_price_data[Date],tbl_naspers_price_data[Market Cap (ZAR B)]) -> 823.0868 | M6: =1-(L6/K6) -> 0.50493491 | N6: =K6-L6 -> 839.49618
A7: =tbl_price_history!A7 -> 43251 | B7: =_xlfn.XLOOKUP(A7,tbl_tencent_market_data[Date],tbl_tencent_market_data[Market Cap (HKD B)]) -> 3208.8622 | C7: =_xlfn.XLOOKUP(A7,tbl_fx_rates_data[Date],tbl_fx_rates_data[HKD_ZAR]) -> 1.62 | D7: =YEAR(EDATE(A7,9)) -> 2019 | E7: =B7*C7 -> 5198.3567 | F7: =_xlfn.XLOOKUP(D7,tbl_ownership[Fiscal_Year],tbl_ownership[Ownership_%]) -> 0.31 | G7: =E7*F7 -> 1611.4906 | H7: =_xlfn.XLOOKUP(D7,tbl_netdebt[Fiscal_Year],tbl_netdebt[Net_debt_USD_B],0) -> -9.1 | I7: =_xlfn.XLOOKUP(A7,tbl_fx_rates_data[Date],tbl_fx_rates_data[USD_ZAR]) -> 12.7 | J7: =H7*I7 -> -115.57 | K7: =G7-J7 -> 1727.0606 | L7: =_xlfn.XLOOKUP(Table6[[#This Row],[Date]],tbl_naspers_price_data[Date],tbl_naspers_price_data[Market Cap (ZAR B)]) -> 814.0774 | M7: =1-(L7/K7) -> 0.52863414 | N7: =K7-L7 -> 912.98318
A8: =tbl_price_history!A8 -> 43281 | B8: =_xlfn.XLOOKUP(A8,tbl_tencent_market_data[Date],tbl_tencent_market_data[Market Cap (HKD B)]) -> 3172.9014 | C8: =_xlfn.XLOOKUP(A8,tbl_fx_rates_data[Date],tbl_fx_rates_data[HKD_ZAR]) -> 1.75 | D8: =YEAR(EDATE(A8,9)) -> 2019 | E8: =B8*C8 -> 5552.5774 | F8: =_xlfn.XLOOKUP(D8,tbl_ownership[Fiscal_Year],tbl_ownership[Ownership_%]) -> 0.31 | G8: =E8*F8 -> 1721.299 | H8: =_xlfn.XLOOKUP(D8,tbl_netdebt[Fiscal_Year],tbl_netdebt[Net_debt_USD_B],0) -> -9.1 | I8: =_xlfn.XLOOKUP(A8,tbl_fx_rates_data[Date],tbl_fx_rates_data[USD_ZAR]) -> 13.72 | J8: =H8*I8 -> -124.852 | K8: =G8-J8 -> 1846.151 | L8: =_xlfn.XLOOKUP(Table6[[#This Row],[Date]],tbl_naspers_price_data[Date],tbl_naspers_price_data[Market Cap (ZAR B)]) -> 937.5768 | M8: =1-(L8/K8) -> 0.49214512 | N8: =K8-L8 -> 908.57421
A9: =tbl_price_history!A9 -> 43312 | B9: =_xlfn.XLOOKUP(A9,tbl_tencent_market_data[Date],tbl_tencent_market_data[Market Cap (HKD B)]) -> 2861.8771 | C9: =_xlfn.XLOOKUP(A9,tbl_fx_rates_data[Date],tbl_fx_rates_data[HKD_ZAR]) -> 1.69 | D9: =YEAR(EDATE(A9,9)) -> 2019 | E9: =B9*C9 -> 4836.5724 | F9: =_xlfn.XLOOKUP(D9,tbl_ownership[Fiscal_Year],tbl_ownership[Ownership_%]) -> 0.31 | G9: =E9*F9 -> 1499.3374 | H9: =_xlfn.XLOOKUP(D9,tbl_netdebt[Fiscal_Year],tbl_netdebt[Net_debt_USD_B],0) -> -9.1 | I9: =_xlfn.XLOOKUP(A9,tbl_fx_rates_data[Date],tbl_fx_rates_data[USD_ZAR]) -> 13.27 | J9: =H9*I9 -> -120.757 | K9: =G9-J9 -> 1620.0944 | L9: =_xlfn.XLOOKUP(Table6[[#This Row],[Date]],tbl_naspers_price_data[Date],tbl_naspers_price_data[Market Cap (ZAR B)]) -> 872.1998 | M9: =1-(L9/K9) -> 0.46163645 | N9: =K9-L9 -> 747.89464
A10: =tbl_price_history!A10 -> 43343 | B10: =_xlfn.XLOOKUP(A10,tbl_tencent_market_data[Date],tbl_tencent_market_data[Market Cap (HKD B)]) -> 2739.3745 | C10: =_xlfn.XLOOKUP(A10,tbl_fx_rates_data[Date],tbl_fx_rates_data[HKD_ZAR]) -> 1.87 | D10: =YEAR(EDATE(A10,9)) -> 2019 | E10: =B10*C10 -> 5122.6302 | F10: =_xlfn.XLOOKUP(D10,tbl_ownership[Fiscal_Year],tbl_ownership[Ownership_%]) -> 0.31 | G10: =E10*F10 -> 1588.0154 | H10: =_xlfn.XLOOKUP(D10,tbl_netdebt[Fiscal_Year],tbl_netdebt[Net_debt_USD_B],0) -> -9.1 | I10: =_xlfn.XLOOKUP(A10,tbl_fx_rates_data[Date],tbl_fx_rates_data[USD_ZAR]) -> 14.68 | J10: =H10*I10 -> -133.588 | K10: =G10-J10 -> 1721.6034 | L10: =_xlfn.XLOOKUP(Table6[[#This Row],[Date]],tbl_naspers_price_data[Date],tbl_naspers_price_data[Market Cap (ZAR B)]) -> 878.5984 | M10: =1-(L10/K10) -> 0.48966271 | N10: =K10-L10 -> 843.00497
A11: =tbl_price_history!A11 -> 43373 | B11: =_xlfn.XLOOKUP(A11,tbl_tencent_market_data[Date],tbl_tencent_market_data[Market Cap (HKD B)]) -> 2604.0676 | C11: =_xlfn.XLOOKUP(A11,tbl_fx_rates_data[Date],tbl_fx_rates_data[HKD_ZAR]) -> 1.81 | D11: =YEAR(EDATE(A11,9)) -> 2019 | E11: =B11*C11 -> 4713.3623 | F11: =_xlfn.XLOOKUP(D11,tbl_ownership[Fiscal_Year],tbl_ownership[Ownership_%]) -> 0.31 | G11: =E11*F11 -> 1461.1423 | H11: =_xlfn.XLOOKUP(D11,tbl_netdebt[Fiscal_Year],tbl_netdebt[Net_debt_USD_B],0) -> -9.1 | I11: =_xlfn.XLOOKUP(A11,tbl_fx_rates_data[Date],tbl_fx_rates_data[USD_ZAR]) -> 14.14 | J11: =H11*I11 -> -128.674 | K11: =G11-J11 -> 1589.8163 | L11: =_xlfn.XLOOKUP(Table6[[#This Row],[Date]],tbl_naspers_price_data[Date],tbl_naspers_price_data[Market Cap (ZAR B)]) -> 820.9896 | M11: =1-(L11/K11) -> 0.48359468 | N11: =K11-L11 -> 768.82671
A12: =tbl_price_history!A12 -> 43404 | B12: =_xlfn.XLOOKUP(A12,tbl_tencent_market_data[Date],tbl_tencent_market_data[Market Cap (HKD B)]) -> 2151.1981 | C12: =_xlfn.XLOOKUP(A12,tbl_fx_rates_data[Date],tbl_fx_rates_data[HKD_ZAR]) -> 1.89 | D12: =YEAR(EDATE(A12,9)) -> 2019 | E12: =B12*C12 -> 4065.7644 | F12: =_xlfn.XLOOKUP(D12,tbl_ownership[Fiscal_Year],tbl_ownership[Ownership_%]) -> 0.31 | G12: =E12*F12 -> 1260.387 | H12: =_xlfn.XLOOKUP(D12,tbl_netdebt[Fiscal_Year],tbl_netdebt[Net_debt_USD_B],0) -> -9.1 | I12: =_xlfn.XLOOKUP(A12,tbl_fx_rates_data[Date],tbl_fx_rates_data[USD_ZAR]) -> 14.78 | J12: =H12*I12 -> -134.498 | K12: =G12-J12 -> 1394.885 | L12: =_xlfn.XLOOKUP(Table6[[#This Row],[Date]],tbl_naspers_price_data[Date],tbl_naspers_price_data[Market Cap (ZAR B)]) -> 697.533 | M12: =1-(L12/K12) -> 0.49993511 | N12: =K12-L12 -> 697.35196
A13: =tbl_price_history!A13 -> 43434 | B13: =_xlfn.XLOOKUP(A13,tbl_tencent_market_data[Date],tbl_tencent_market_data[Market Cap (HKD B)]) -> 2513.8024 | C13: =_xlfn.XLOOKUP(A13,tbl_fx_rates_data[Date],tbl_fx_rates_data[HKD_ZAR]) -> 1.77 | D13: =YEAR(EDATE(A13,9)) -> 2019 | E13: =B13*C13 -> 4449.4303 | F13: =_xlfn.XLOOKUP(D13,tbl_ownership[Fiscal_Year],tbl_ownership[Ownership_%]) -> 0.31 | G13: =E13*F13 -> 1379.3234 | H13: =_xlfn.XLOOKUP(D13,tbl_netdebt[Fiscal_Year],tbl_netdebt[Net_debt_USD_B],0) -> -9.1 | I13: =_xlfn.XLOOKUP(A13,tbl_fx_rates_data[Date],tbl_fx_rates_data[USD_ZAR]) -> 13.86 | J13: =H13*I13 -> -126.126 | K13: =G13-J13 -> 1505.4494 | L13: =_xlfn.XLOOKUP(Table6[[#This Row],[Date]],tbl_naspers_price_data[Date],tbl_naspers_price_data[Market Cap (ZAR B)]) -> 743.3504 | M13: =1-(L13/K13) -> 0.50622691 | N13: =K13-L13 -> 762.09899
A14: =tbl_price_history!A14 -> 43465 | B14: =_xlfn.XLOOKUP(A14,tbl_tencent_market_data[Date],tbl_tencent_market_data[Market Cap (HKD B)]) -> 2529.8758 | C14: =_xlfn.XLOOKUP(A14,tbl_fx_rates_data[Date],tbl_fx_rates_data[HKD_ZAR]) -> 1.83 | D14: =YEAR(EDATE(A14,9)) -> 2019 | E14: =B14*C14 -> 4629.6727 | F14: =_xlfn.XLOOKUP(D14,tbl_ownership[Fiscal_Year],tbl_ownership[Ownership_%]) -> 0.31 | G14: =E14*F14 -> 1435.1985 | H14: =_xlfn.XLOOKUP(D14,tbl_netdebt[Fiscal_Year],tbl_netdebt[Net_debt_USD_B],0) -> -9.1 | I14: =_xlfn.XLOOKUP(A14,tbl_fx_rates_data[Date],tbl_fx_rates_data[USD_ZAR]) -> 14.35 | J14: =H14*I14 -> -130.585 | K14: =G14-J14 -> 1565.7835 | L14: =_xlfn.XLOOKUP(Table6[[#This Row],[Date]],tbl_naspers_price_data[Date],tbl_naspers_price_data[Market Cap (ZAR B)]) -> 778.1254 | M14: =1-(L14/K14) -> 0.50304408 | N14: =K14-L14 -> 787.65814
A15: =tbl_price_history!A15 -> 43496 | B15: =_xlfn.XLOOKUP(A15,tbl_tencent_market_data[Date],tbl_tencent_market_data[Market Cap (HKD B)]) -> 2787.7762 | C15: =_xlfn.XLOOKUP(A15,tbl_fx_rates_data[Date],tbl_fx_rates_data[HKD_ZAR]) -> 1.69 | D15: =YEAR(EDATE(A15,9)) -> 2019 | E15: =B15*C15 -> 4711.3418 | F15: =_xlfn.XLOOKUP(D15,tbl_ownership[Fiscal_Year],tbl_ownership[Ownership_%]) -> 0.31 | G15: =E15*F15 -> 1460.5159 | H15: =_xlfn.XLOOKUP(D15,tbl_netdebt[Fiscal_Year],tbl_netdebt[Net_debt_USD_B],0) -> -9.1 | I15: =_xlfn.XLOOKUP(A15,tbl_fx_rates_data[Date],tbl_fx_rates_data[USD_ZAR]) -> 13.25 | J15: =H15*I15 -> -120.575 | K15: =G15-J15 -> 1581.0909 | L15: =_xlfn.XLOOKUP(Table6[[#This Row],[Date]],tbl_naspers_price_data[Date],tbl_naspers_price_data[Market Cap (ZAR B)]) -> 817.8866 | M15: =1-(L15/K15) -> 0.48270743 | N15: =K15-L15 -> 763.20435
A16: =tbl_price_history!A16 -> 43524 | B16: =_xlfn.XLOOKUP(A16,tbl_tencent_market_data[Date],tbl_tencent_market_data[Market Cap (HKD B)]) -> 2705.5931 | C16: =_xlfn.XLOOKUP(A16,tbl_fx_rates_data[Date],tbl_fx_rates_data[HKD_ZAR]) -> 1.79 | D16: =YEAR(EDATE(A16,9)) -> 2019 | E16: =B16*C16 -> 4843.0117 | F16: =_xlfn.XLOOKUP(D16,tbl_ownership[Fiscal_Year],tbl_ownership[Ownership_%]) -> 0.31 | G16: =E16*F16 -> 1501.3336 | H16: =_xlfn.XLOOKUP(D16,tbl_netdebt[Fiscal_Year],tbl_netdebt[Net_debt_USD_B],0) -> -9.1 | I16: =_xlfn.XLOOKUP(A16,tbl_fx_rates_data[Date],tbl_fx_rates_data[USD_ZAR]) -> 14.08 | J16: =H16*I16 -> -128.128 | K16: =G16-J16 -> 1629.4616 | L16: =_xlfn.XLOOKUP(Table6[[#This Row],[Date]],tbl_naspers_price_data[Date],tbl_naspers_price_data[Market Cap (ZAR B)]) -> 845.0218 | M16: =1-(L16/K16) -> 0.48141043 | N16: =K16-L16 -> 784.43983
A17: =tbl_price_history!A17 -> 43555 | B17: =_xlfn.XLOOKUP(A17,tbl_tencent_market_data[Date],tbl_tencent_market_data[Market Cap (HKD B)]) -> 2908.5535 | C17: =_xlfn.XLOOKUP(A17,tbl_fx_rates_data[Date],tbl_fx_rates_data[HKD_ZAR]) -> 1.84 | D17: =YEAR(EDATE(A17,9)) -> 2019 | E17: =B17*C17 -> 5351.7384 | F17: =_xlfn.XLOOKUP(D17,tbl_ownership[Fiscal_Year],tbl_ownership[Ownership_%]) -> 0.31 | G17: =E17*F17 -> 1659.0389 | H17: =_xlfn.XLOOKUP(D17,tbl_netdebt[Fiscal_Year],tbl_netdebt[Net_debt_USD_B],0) -> -9.1 | I17: =_xlfn.XLOOKUP(A17,tbl_fx_rates_data[Date],tbl_fx_rates_data[USD_ZAR]) -> 14.48 | J17: =H17*I17 -> -131.768 | K17: =G17-J17 -> 1790.8069 | L17: =_xlfn.XLOOKUP(Table6[[#This Row],[Date]],tbl_naspers_price_data[Date],tbl_naspers_price_data[Market Cap (ZAR B)]) -> 924.587 | M17: =1-(L17/K17) -> 0.48370369 | N17: =K17-L17 -> 866.21991
... A89: =tbl_price_history!A89 -> 45747 | B89: =_xlfn.XLOOKUP(A89,tbl_tencent_market_data[Date],tbl_tencent_market_data[Market Cap (HKD B)]) -> 4474.2087 | C89: =_xlfn.XLOOKUP(A89,tbl_fx_rates_data[Date],tbl_fx_rates_data[HKD_ZAR]) -> 2.35 | D89: =YEAR(EDATE(A89,9)) -> 2025 | E89: =B89*C89 -> 10514.39 | F89: =_xlfn.XLOOKUP(D89,tbl_ownership[Fiscal_Year],tbl_ownership[Ownership_%]) -> 0.23 | G89: =E89*F89 -> 2418.3098 | H89: =_xlfn.XLOOKUP(D89,tbl_netdebt[Fiscal_Year],tbl_netdebt[Net_debt_USD_B],0) -> -1.9 | I89: =_xlfn.XLOOKUP(A89,tbl_fx_rates_data[Date],tbl_fx_rates_data[USD_ZAR]) -> 18.31 | J89: =H89*I89 -> -34.789 | K89: =G89-J89 -> 2453.0988 | L89: =_xlfn.XLOOKUP(Table6[[#This Row],[Date]],tbl_naspers_price_data[Date],tbl_naspers_price_data[Market Cap (ZAR B)]) -> 842.11792 | M89: =1-(L89/K89) -> 0.6567126 | N89: =K89-L89 -> 1610.9809

Sheet tbl_shares_outstanding
A1: tbl_shares_outstanding
A3: Notes
A4: Naspers N-shares outstanding (millions). Naspers has conducted significant share buybacks since 2021 via the cross-holding unwind with Prosus. Share count used in per-share NAV calculation sourced from latest published results. For the valuation dashboard, implied share price = (NAV × (1 - discount)) / shares.
A6: Fiscal Year | B6: Shares Outstanding (millions) | C6: Source
A7: 2019 | B7: 2140 | C7: FY2019 Annual Report
A8: 2020 | B8: 2140 | C8: FY2020 Annual Report
A9: 2021 | B9: 2040 | C9: FY2021 Annual Report — post buyback
A10: 2022 | B10: 1900 | C10: FY2022 Annual Report — continued buyback programme
A11: 2023 | B11: 1820 | C11: FY2023 Annual Report
A12: 2024 | B12: 1640 | C12: FY2024 Annual Report
A13: 2025 | B13: 1480 | C13: FY2025 est. — based on latest disclosed count
A15: Note: Shares outstanding are in millions. These figures reflect Naspers N-shares (the primary JSE-listed class). Buyback impact is material — share count has declined ~31% from 2019 to 2025, which is NAV-accretive on a per-share basis even if aggregate NAV is flat.

Sheet tbl_nav_components
A3: tbl_ownership
A5: Fiscal_Year | B5: Ownership_%
A6: 2019 | B6: 0.31
A7: 2020 | B7: 0.31
A8: 2021 | B8: 0.29
A9: 2022 | B9: 0.26
A10: 2023 | B10: 0.26
A11: 2024 | B11: 0.24
A12: 2025 | B12: 0.23
A14: tbl_netdebt
A16: Fiscal_Year | B16: Net_debt_USD_B
A17: 2019 | B17: -9.1
A18: 2020 | B18: -4.4
A19: 2021 | B19: -3.9
A20: 2022 | B20: 0.8
A21: 2023 | B21: 0.4
A22: 2024 | B22: 0.7
A23: 2025 | B23: -1.9

Sheet assumptions_core
A3: tbl_assumptions_core
H4: Active_Scenario | J4: Base
A5: Assumption | B5: Base | C5: Bull | D5: Bear | E5: Active_Value | F5: Unit | G5: Notes
A6: Target_Holding_Discount_% | B6: 0.5 | C6: 0.35 | D6: 0.65 | E6: =IF($J$4="Bull",Table7[[#This Row],[Bull]],IF($J$4="Bear",Table7[[#This Row],[Bear]],Table7[[#This Row],[Base]])) -> 0.5 | F6: % | G6: Discount applied to NAV
A7: Tencent_Value_Shock_% | B7: 0 | C7: 0.2 | D7: -0.25 | E7: =IF($J$4="Bull",Table7[[#This Row],[Bull]],IF($J$4="Bear",Table7[[#This Row],[Bear]],Table7[[#This Row],[Base]])) -> 0 | F7: % | G7: Shock to Tencent HKD market cap
A8: HKD_ZAR_Shock_% | B8: 0 | C8: -0.05 | D8: 0.1 | E8: =IF($J$4="Bull",Table7[[#This Row],[Bull]],IF($J$4="Bear",Table7[[#This Row],[Bear]],Table7[[#This Row],[Base]])) -> 0 | F8: % | G8: FX stress
A9: Corporate_NetDebt_Shock_USD_B | B9: 0 | C9: -0.5 | D9: 0.5 | E9: =IF($J$4="Bull",Table7[[#This Row],[Bull]],IF($J$4="Bear",Table7[[#This Row],[Bear]],Table7[[#This Row],[Base]])) -> 0 | F9: USD B | G9: Negative = more net cash
A11: Structural Note
A12: Ownership % assumption represents Naspers effective economic interest in Tencent (via Prosus). This is NOT a direct holding post-2019. Bull case assumes no further dilution. Bear case should incorporate risk of further ownership reduction through Prosus restructuring.

Sheet Valuation_Dashboard
A2: Latest Date | B2: {=LOOKUP(2,1/(calc_lookthrough_nav!A:A<>""),calc_lookthrough_nav!A:A)} -> 45747 | D2: Scenario Comparison | H2: Current_Discount | I2: Current_Share_Price
A3: Latest NAV (ZAR B) | B3: =_xlfn.XLOOKUP(B2,calc_lookthrough_nav!A:A,calc_lookthrough_nav!K:K) -> 2453.0988 | H3: =B8 -> 0.6567126 | I3: =B4 -> 842.11792
A4: Latest Market Cap (ZAR B) | B4: =_xlfn.XLOOKUP(B2,calc_lookthrough_nav!A:A,calc_lookthrough_nav!L:L) -> 842.11792 | D4: Metric | E4: Base | F4: Bull | G4: Bear
A5: Target Holding Discount (%) | B5: =_xlfn.XLOOKUP("Target_Holding_Discount_%",assumptions_core!A:A,assumptions_core!E:E) -> 0.5 | D5: Target Discount (%) | E5: =_xlfn.XLOOKUP("Target_Holding_Discount_%",assumptions_core!A:A,assumptions_core!B:B) -> 0.5 | F5: =_xlfn.XLOOKUP("Target_Holding_Discount_%",assumptions_core!A:A,assumptions_core!C:C) -> 0.35 | G5: =_xlfn.XLOOKUP("Target_Holding_Discount_%",assumptions_core!A:A,assumptions_core!D:D) -> 0.65
A6: Scenario Implied Market Cap (ZAR B) | B6: =B3*(1-B5) -> 1226.5494 | D6: Implied Market Cap (ZAR B) | E6: =$B$3*(1-E5) -> 1226.5494 | F6: =$B$3*(1-F5) -> 1594.5142 | G6: =$B$3*(1-G5) -> 858.58458
A7: Scenario Upside (%) | B7: =(B6/B4)-1 -> 0.45650552 | D7: Upside (%) | E7: =(E6/$B$4)-1 -> 0.45650552 | F7: =(F6/$B$4)-1 -> 0.89345718 | G7: =(G6/$B$4)-1 -> 0.019553866
A8: Current NAV Discount (%) | B8: =1-(B4/B3) -> 0.6567126 | D8: Implied Share Price | E8: {=E6 / LOOKUP(2,1/(tbl_naspers_price_data[Shares Outstanding (B)]<>""),tbl_naspers_price_data[Shares Outstanding (B)])} -> 1316.0401 | F8: =F6 / _xlfn.XLOOKUP($B$2,tbl_naspers_price_data[Date],tbl_naspers_price_data[Shares Outstanding (B)]) -> 1710.8522 | G8: =G6 / _xlfn.XLOOKUP($B$2,tbl_naspers_price_data[Date],tbl_naspers_price_data[Shares Outstanding (B)]) -> 921.22809
A9: Discount Gap (Current - Target) | B9: =B8-B5 -> 0.1567126
D11: Holding Discount Sensitivity
D13: Discount (%) | E13: Implied Share Price
D14: 0.3 | E14: =($B$3*(1-D14)) / _xlfn.XLOOKUP($B$2,tbl_naspers_price_data[Date],tbl_naspers_price_data[Shares Outstanding (B)]) -> 1842.4562
D15: 0.35 | E15: =($B$3*(1-D15)) / _xlfn.XLOOKUP($B$2,tbl_naspers_price_data[Date],tbl_naspers_price_data[Shares Outstanding (B)]) -> 1710.8522
D16: 0.4 | E16: =($B$3*(1-D16)) / _xlfn.XLOOKUP($B$2,tbl_naspers_price_data[Date],tbl_naspers_price_data[Shares Outstanding (B)]) -> 1579.2482
D17: 0.45 | E17: =($B$3*(1-D17)) / _xlfn.XLOOKUP($B$2,tbl_naspers_price_data[Date],tbl_naspers_price_data[Shares Outstanding (B)]) -> 1447.6441
D18: 0.5 | E18: =($B$3*(1-D18)) / _xlfn.XLOOKUP($B$2,tbl_naspers_price_data[Date],tbl_naspers_price_data[Shares Outstanding (B)]) -> 1316.0401
D19: 0.55 | E19: =($B$3*(1-D19)) / _xlfn.XLOOKUP($B$2,tbl_naspers_price_data[Date],tbl_naspers_price_data[Shares Outstanding (B)]) -> 1184.4361
D20: 0.6 | E20: =($B$3*(1-D20)) / _xlfn.XLOOKUP($B$2,tbl_naspers_price_data[Date],tbl_naspers_price_data[Shares Outstanding (B)]) -> 1052.8321
D21: 0.65 | E21: =($B$3*(1-D21)) / _xlfn.XLOOKUP($B$2,tbl_naspers_price_data[Date],tbl_naspers_price_data[Shares Outstanding (B)]) -> 921.22809
D22: 0.7 | E22: =($B$3*(1-D22)) / _xlfn.XLOOKUP($B$2,tbl_naspers_price_data[Date],tbl_naspers_price_data[Shares Outstanding (B)]) -> 789.62408
D38: Investment Takeaway
D39: • Current discount: 65.7%
D40: • Target discount: 50%
D41: • Discount gap: 15.7%
D42: • Implied upside to target: 45.7%
A44: Data Currency Note
A45: Price series ends March 2025. Latest discount (65.7%) and NAV figures reflect March 2025 data. To update: extend tbl_price_history, tbl_tencent_market, and tbl_fx_rates with monthly data through the most recent month-end. All calc_lookthrough_nav calculations will update automatically via the existing formulas. Target update frequency: monthly.
A47: Per-Share Price Methodology
A48: Implied Share Price = (NAV_ZAR_B × (1 - Target_Discount)) / Shares_Outstanding_B Share count used: ~1.48B shares (FY2025 est.). See tbl_shares_outstanding for full history. Note: Naspers N-share count has declined materially due to the Prosus cross-holding buyback programme — this is per-share NAV accretive. The buyback effect is not modelled dynamically here but is captured in the declining share count by fiscal year.

Sheet model_overview
A3: Look-Through NAV Valuation Model – Naspers
A6: Objective
A8: Estimate intrinsic equity value using look-through NAV and discount scenarios.
A10: Methodology
A12: Tencent market cap (HKD)
A13: FX conversion to ZAR
A14: Ownership %
A15: ↳ Ownership % = Effective economic interest in Tencent (indirect, via Prosus) Structure: Naspers (~57% of Prosus) → Prosus (~24% of Tencent as of 2025) This model applies the blended effective interest directly to Tencent market cap (i.e., 0.57 × 0.24 ≈ 13.7% effective in 2025, declining from 31% direct in 2018–2020) Note: Pre-2019 Naspers held Tencent directly. Post-2019 Prosus restructuring introduced the holding company layer. Ownership % in tbl_nav_components reflects blended effective interest.
A16: ↳ Ownership % = Effective economic interest in Tencent (indirect, via Prosus) Structure: Naspers (~57% of Prosus) → Prosus (~24% of Tencent as of 2025) This model applies the blended effective interest directly to Tencent market cap (i.e., 0.57 × 0.24 ≈ 13.7% effective in 2025, declining from 31% direct in 2018–2020) Note: Pre-2019 Naspers held Tencent directly. Post-2019 Prosus restructuring introduced the holding company layer. Ownership % in tbl_nav_components reflects blended effective interest.
A17: ↳ Ownership % = Effective economic interest in Tencent (indirect, via Prosus) Structure: Naspers (~57% of Prosus) → Prosus (~24% of Tencent as of 2025) This model applies the blended effective interest directly to Tencent market cap (i.e., 0.57 × 0.24 ≈ 13.7% effective in 2025, declining from 31% direct in 2018–2020) Note: Pre-2019 Naspers held Tencent directly. Post-2019 Prosus restructuring introduced the holding company layer. Ownership % in tbl_nav_components reflects blended effective interest.
A18: ↳ Ownership % = Effective economic interest in Tencent (indirect, via Prosus) Structure: Naspers (~57% of Prosus) → Prosus (~24% of Tencent as of 2025) This model applies the blended effective interest directly to Tencent market cap (i.e., 0.57 × 0.24 ≈ 13.7% effective in 2025, declining from 31% direct in 2018–2020) Note: Pre-2019 Naspers held Tencent directly. Post-2019 Prosus restructuring introduced the holding company layer. Ownership % in tbl_nav_components reflects blended effective interest.
A19: ↳ Ownership % = Effective economic interest in Tencent (indirect, via Prosus) Structure: Naspers (~57% of Prosus) → Prosus (~24% of Tencent as of 2025) This model applies the blended effective interest directly to Tencent market cap (i.e., 0.57 × 0.24 ≈ 13.7% effective in 2025, declining from 31% direct in 2018–2020) Note: Pre-2019 Naspers held Tencent directly. Post-2019 Prosus restructuring introduced the holding company layer. Ownership % in tbl_nav_components reflects blended effective interest.
... A38: ↳ Ownership % = Effective economic interest in Tencent (indirect, via Prosus) Structure: Naspers (~57% of Prosus) → Prosus (~24% of Tencent as of 2025) This model applies the blended effective interest directly to Tencent market cap (i.e., 0.57 × 0.24 ≈ 13.7% effective in 2025, declining from 31% direct in 2018–2020) Note: Pre-2019 Naspers held Tencent directly. Post-2019 Prosus restructuring introduced the holding company layer. Ownership % in tbl_nav_components reflects blended effective interest.
